pycounts_fe/__init__.py
pycounts_fe/plotting.py
pycounts_fe/pycounts_fe.py
pycounts_fe-0.1.0.dist-info/LICENSE
pycounts_fe-0.1.0.dist-info/METADATA
pycounts_fe-0.1.0.dist-info/WHEEL
pycounts_fe-0.1.0.dist-info/RECORD
